cppscripts/electric.cpp
cppscripts/electric.h
modchem/__init__.py
modchem/catalogs/elements.py
modchem/commands/__init__.py
modchem/commands/command.py
modchem/core/app.py
modchem/core/logger.py
modchem/core/params.py
modchem/core/project.py
modchem/database/datasets.py
modchem/database/redox_periodictable.csv
modchem/entities/atom.py
modchem/entities/ion.py
modchem/entities/molecula.py
modchem/experiment/experimental.py
modchem/templates/__init__.py
modchem/templates/app.py-tpl
modchem/templates/main.py-tpl
modchem/templates/params.py-tpl
modchemlib-0.0.8.dist-info/METADATA
modchemlib-0.0.8.dist-info/WHEEL
modchemlib-0.0.8.dist-info/entry_points.txt
modchemlib-0.0.8.dist-info/top_level.txt
modchemlib-0.0.8.dist-info/RECORD
